wktools_langflow/__init__.py
wktools_langflow/card_toolkit.py
wktools_langflow/loan_toolkit.py
wktools_langflow/movie_toolkit.py
wktools_langflow/wrapper/__init__.py
wktools_langflow/wrapper/card_wrapper.py
wktools_langflow/wrapper/loan_wrapper.py
wktools_langflow/wrapper/tmdb_wrapper.py
wktools_langflow-0.1.44.dist-info/LICENSE
wktools_langflow-0.1.44.dist-info/METADATA
wktools_langflow-0.1.44.dist-info/WHEEL
wktools_langflow-0.1.44.dist-info/top_level.txt
wktools_langflow-0.1.44.dist-info/RECORD
