Metadata-Version: 2.1
Name: wktools-langflow
Version: 0.1.44
Summary: A tools for langflow
Home-page: https://github.com/kokhou/jwtools
Author: kokhou
Author-email: kokhou.choi@gmail.com
Classifier: Programming Language :: Python :: 3
Classifier: License :: OSI Approved :: MIT License
Classifier: Operating System :: OS Independent
Requires-Python: >=3.10
License-File: LICENSE
